{
  "project_info": {
    "project_number": "406819133999",
    "project_id": "recyclerviewance",
    "storage_bucket": "recyclerviewance.appspot.com"
  },
  "client": [
    {
      "client_info": {
        "mobilesdk_app_id": "1:406819133999:android:3821ed0c088409abba84da",
        "android_client_info": {
          "package_name": "com.example.recyclerviewance"
        }
      },
      "oauth_client": [
        {
          "client_id": "406819133999-vk20d3fvbtmemdvlod42igk9ccgm5a0v.apps.googleusercontent.com",
          "client_type": 3
        }
      ],
      "api_key": [
        {
          "current_key": "AIzaSyBlGLvfulnOtnV1WZ4YgJPdHxnOBdAxMH0"
        }
      ],
      "services": {
        "appinvite_service": {
          "other_platform_oauth_client": [
            {
              "client_id": "406819133999-vk20d3fvbtmemdvlod42igk9ccgm5a0v.apps.googleusercontent.com",
              "client_type": 3
            }
          ]
        }
      }
    }
  ],
  "configuration_version": "1"
}